scrapewiki/__init__.py
scrapewiki/constants.py
scrapewiki/core.py
scrapewiki/errors.py
scrapewiki/http.py
scrapewiki/searcher.py
scrapewiki/wiki.py
scrapewiki/abc/__init__.py
scrapewiki/abc/coroutine_handler.py
scrapewiki/structures/__init__.py
scrapewiki/structures/dataclasses.py
scrapewiki/structures/enums.py
scrapewiki/util/__init__.py
scrapewiki/util/converters.py
scrapewiki-0.1.5b0.dist-info/LICENSE
scrapewiki-0.1.5b0.dist-info/METADATA
scrapewiki-0.1.5b0.dist-info/WHEEL
scrapewiki-0.1.5b0.dist-info/top_level.txt
scrapewiki-0.1.5b0.dist-info/RECORD
