Metadata-Version: 2.1
Name: scrapewiki
Version: 0.1.5b0
Summary: A simple asynchronous and synchronous Wikipedia scraper.
Author: m-y-x-i
Author-email: myxi@duck.com
License: MIT
Keywords: wikipedia,scraper,asynchronous
Platform: UNKNOWN
Classifier: Programming Language :: Python :: 3
Classifier: License :: OSI Approved :: MIT License
License-File: LICENSE
Requires-Dist: arrow (==1.2.2)
Requires-Dist: httpx (==0.22.0)
Requires-Dist: selectolax (==0.3.6)
Requires-Dist: trio (==0.19.0)
Requires-Dist: yarl (==1.6.3)
